{
  "generatedAt": "2026-07-20T23:10:03.256Z",
  "periods": {
    "last_7d": {
      "since": "2026-07-13T23:10:03.256Z",
      "until": "2026-07-20T23:10:03.256Z",
      "scheduled": 0,
      "attended": 0,
      "won": 1,
      "wonValue": 0,
      "currency": "BRL"
    },
    "last_30d": {
      "since": "2026-06-20T23:10:03.256Z",
      "until": "2026-07-20T23:10:03.256Z",
      "scheduled": 0,
      "attended": 0,
      "won": 115,
      "wonValue": 735889,
      "currency": "BRL"
    }
  }
}